yamlstore/__init__.py
yamlstore/documents.py
yamlstore/py.typed
yamlstore-0.7.3.dist-info/LICENSE
yamlstore-0.7.3.dist-info/METADATA
yamlstore-0.7.3.dist-info/WHEEL
yamlstore-0.7.3.dist-info/top_level.txt
yamlstore-0.7.3.dist-info/RECORD
